MANIFEST.in
README.md
setup.py
Underscore.egg-info/PKG-INFO
Underscore.egg-info/SOURCES.txt
Underscore.egg-info/dependency_links.txt
Underscore.egg-info/requires.txt
Underscore.egg-info/top_level.txt
bin/_
underscore/__init__.py
underscore/base.py
underscore/codegen.py
underscore/constant_visitor.py
underscore/declaration.py
underscore/environment.py
underscore/frame.py
underscore/utils.py
underscore/variable_visitor.py