Metadata-Version: 1.0
Name: Underscore
Version: 0.0.5
Summary: Obfuscating code by changing the variable names to underscores
Home-page: https://github.com/Doboy/Dunderscore
Author: Huan Do
Author-email: doboy0@gmail.com
License: UNKNOWN
Platform: UNKNOWN
